ape/common/__init__.py
ape/common/evaluator/__init__.py
ape/common/evaluator/evaluator.py
ape/common/generator/__init__.py
ape/common/generator/base_generator.py
ape/common/generator/generator.py
ape/common/global_metric/__init__.py
ape/common/global_metric/average.py
ape/common/global_metric/global_metric_base.py
ape/common/metric/__init__.py
ape/common/metric/cosine_similarity.py
ape/common/metric/json_match.py
ape/common/metric/metric_base.py
ape/common/metric/semantic_f1.py
ape/common/metric_prompts/__init__.py
ape/common/metric_prompts/binary-judge.prompt
ape/common/metric_prompts/semantic-precision.prompt
ape/common/metric_prompts/semantic-recall.prompt
ape/common/metric_prompts/statement-analysis.prompt
ape/common/prompt/__init__.py
ape/common/prompt/cost_tracker.py
ape/common/prompt/prompt_base.py
ape/common/prompt/utils.py
ape/common/types/__init__.py
ape/common/types/dataset_item.py
ape/common/types/eval_result.py
ape/common/types/response_format.py
ape/common/utils/__init__.py
ape/common/utils/logging.py
ape_common-0.2.1.dist-info/METADATA
ape_common-0.2.1.dist-info/WHEEL
ape_common-0.2.1.dist-info/top_level.txt
ape_common-0.2.1.dist-info/RECORD
